aisbom/__init__.py
aisbom/cli.py
aisbom/generator.py
aisbom/remote.py
aisbom/safety.py
aisbom/scanner.py
aisbom_cli-0.3.1.dist-info/METADATA
aisbom_cli-0.3.1.dist-info/WHEEL
aisbom_cli-0.3.1.dist-info/entry_points.txt
aisbom_cli-0.3.1.dist-info/licenses/LICENSE
aisbom_cli-0.3.1.dist-info/RECORD
