Metadata-Version: 2.4
Name: aisbom-cli
Version: 0.3.1
Summary: An AI Supply Chain security tool that that detects Pickle bombs and generates CycloneDX SBOMs for Machine Learning models.
License-File: LICENSE
Author: Ajoy L
Author-email: lab700xdev@gmail.com
Requires-Python: >=3.11,<4.0
Classifier: Programming Language :: Python :: 3
Classifier: Programming Language :: Python :: 3.11
Classifier: Programming Language :: Python :: 3.12
Classifier: Programming Language :: Python :: 3.13
Classifier: Programming Language :: Python :: 3.14
Requires-Dist: click (<8.2.0)
Requires-Dist: cyclonedx-python-lib (>=8.5.0,<9.0.0)
Requires-Dist: pip-requirements-parser (>=32.0.1,<33.0.0)
Requires-Dist: requests (>=2.32.3,<3.0.0)
Requires-Dist: rich (>=13.7.1,<14.0.0)
Requires-Dist: typer[all] (>=0.12.5,<0.13.0)
Project-URL: Homepage, https://www.aisbom.io/
Project-URL: Repository, https://github.com/Lab700xOrg/aisbom
